punycode/__init__.py
punycode/punycode.py
punycode/test.py
punycode-0.2.1.dist-info/LICENSE
punycode-0.2.1.dist-info/METADATA
punycode-0.2.1.dist-info/WHEEL
punycode-0.2.1.dist-info/top_level.txt
punycode-0.2.1.dist-info/RECORD
