Metadata-Version: 2.1
Name: punycode
Version: 0.2.1
Summary: Punycode Converter Library for Python
Home-page: https://github.com/Yutsuro/punycode
Author: Yutsuro
Author-email: Yuki@utsu.ro
License: MIT
Keywords: Punycode Converter Python
Classifier: License :: OSI Approved :: MIT License
Classifier: Programming Language :: Python :: 3
Classifier: Programming Language :: Python :: 3.6
Classifier: Programming Language :: Python :: 3.7
Classifier: Programming Language :: Python :: 3.8
Classifier: Programming Language :: Python :: 3.9
Classifier: Programming Language :: Python :: 3 :: Only
Classifier: Topic :: Internet :: Name Service (DNS)
Classifier: Topic :: Software Development :: Libraries :: Python Modules
License-File: LICENSE
Requires-Dist: idna (==3.4)
Requires-Dist: wincertstore (==0.2)
